django_testing.py
django_testing_recipe.py
django_pastedeploy_settings-1.0.2.dist-info/pbr.json
django_pastedeploy_settings-1.0.2.dist-info/WHEEL
django_pastedeploy_settings-1.0.2.dist-info/metadata.json
django_pastedeploy_settings-1.0.2.dist-info/DESCRIPTION.rst
django_pastedeploy_settings-1.0.2.dist-info/METADATA
django_pastedeploy_settings-1.0.2.dist-info/top_level.txt
django_pastedeploy_settings-1.0.2.dist-info/entry_points.txt
django_pastedeploy_settings-1.0.2.dist-info/RECORD
tests/mock_django_settings/settings6.py
tests/mock_django_settings/iterables_module.py
tests/mock_django_settings/__init__.py
tests/mock_django_settings/settings5.py
tests/mock_django_settings/empty_module2.py
tests/mock_django_settings/settings2.py
tests/mock_django_settings/settings3.py
tests/mock_django_settings/settings4.py
tests/mock_django_settings/debug_settings.py
tests/mock_django_settings/empty_module.py
tests/mock_django_settings/one_member_module.py
tests/mock_django_settings/settings.py
tests/mock_django_settings/read_only_empty_module.py
django_pastedeploy_settings/__init__.py
django_pastedeploy_settings/factories.py
django_pastedeploy_settings/buildout_options.py
