Metadata-Version: 2.0
Name: django-pastedeploy-settings
Version: 1.0.2
Summary: Conversion of Paste Deployment configuration to Django settings
Home-page: http://pythonhosted.org/django-pastedeploy-settings/
Author: 2degrees Limited
Author-email: 2degrees-floss@googlegroups.com
License: BSD (http://dev.2degreesnetwork.com/p/2degrees-license.html)
Keywords: django wsgi paste pastedeploy web webtest nose nosetests
Platform: UNKNOWN
Classifier: Development Status :: 5 - Production/Stable
Classifier: Environment :: Web Environment
Classifier: Framework :: Django
Classifier: Framework :: Paste
Classifier: Intended Audience :: Developers
Classifier: License :: OSI Approved :: BSD License
Classifier: Natural Language :: English
Classifier: Operating System :: OS Independent
Classifier: Programming Language :: Python :: 2
Classifier: Topic :: Internet :: WWW/HTTP
Classifier: Topic :: Internet :: WWW/HTTP :: WSGI
Requires-Dist: Django (>=1.4)
Requires-Dist: PasteDeploy (>=1.3.3)
Requires-Dist: Paste (>=1.7.2)
Requires-Dist: setuptools
Provides-Extra: buildout-options
Requires-Dist: deployrecipes (>=1.0); extra == 'buildout-options'
Provides-Extra: nose-buildout
Requires-Dist: zc.recipe.egg (>=1.2.2); extra == 'nose-buildout'
